task3/task3/counter.sv
module counter #(
  parameter WIDTH = 8
)(
  // interface signals
  input  logic             clk,      // clock 
  input  logic             rst,      // reset 
  input  logic             ld,       // load counter from data
  input  logic [WIDTH-1:0] v,        // value to preload
  output logic [WIDTH-1:0] count     // count output
);

always_ff @ (posedge clk)
  if (rst) count <= {WIDTH{1'b0}};
  else     count <= ld ? v : count + {{WIDTH-1{1'b0}},1'b1};

endmodule

// module counter #(
//     parameter WIDTH = 8
// )(
//     // interface signals
//     input logic clk,       // clock
//     input logic rst,       // reset
//     input logic vbuddy_flag,
//     output logic [WIDTH-1:0] count  // count output
// );

// always_ff @(posedge clk) begin
//     if (rst) begin
//         count <= {WIDTH{1'b0}};
//     end else if (vbuddy_flag) begin 
//         count <= count + {{WIDTH-1{1'b0}},1'b1};
//     end
// end


// endmodule

task3/task3/counter.vcd
$version Generated by VerilatedVcd $end
$timescale 1ps $end

 $scope module TOP $end
  $var wire  1 # clk $end
  $var wire  8 ' count [7:0] $end
  $var wire  1 % ld $end
  $var wire  1 $ rst $end
  $var wire  8 & v [7:0] $end
  $scope module counter $end
   $var wire 32 ( WIDTH [31:0] $end
   $var wire  1 # clk $end
   $var wire  8 ' count [7:0] $end
   $var wire  1 % ld $end
   $var wire  1 $ rst $end
   $var wire  8 & v [7:0] $end
  $upscope $end
 $upscope $end
$enddefinitions $end


#0
1#
1$
0%
b00110011 &
b00000000 '
b00000000000000000000000000001000 (
#1
0#
#2
1#
1%
#3
0#
#4
1#
#5
0#
#6
1#
0$
#7
0#
#8
1#
b00110011 '
#9
0#
#10
1#
#11
0#
#12
1#
#13
0#
#14
1#
#15
0#
#16
1#
#17
0#
#18
1#
#19
0#
#20
1#
#21
0#
#22
1#
#23
0#
#24
1#
#25
0#
#26
1#
#27
0#
#28
1#
#29
0#
#30
1#
#31
0#
#32
1#
1$
#33
0#
#34
1#
0$
b00101111 &
b00000000 '
#35
0#
#36
1#
b00101010 &
b00101111 '
#37
0#
#38
1#
b00100110 &
b00101010 '
#39
0#
#40
1#
b00100110 '
